peepapp_core/__init__.py
peepapp_core/analysis/__init__.py
peepapp_core/analysis/apk_signature.py
peepapp_core/analysis/certificate.py
peepapp_core/analysis/static_analysis.py
peepapp_core/analysis/test_peepapp_analyze.py
peepapp_core/analysis/utils.py
peepapp_core/helper/__init__.py
peepapp_core/helper/connector.py
peepapp_core-0.1.0.dist-info/LICENSE
peepapp_core-0.1.0.dist-info/LICENSE:Zone.Identifier
peepapp_core-0.1.0.dist-info/METADATA
peepapp_core-0.1.0.dist-info/WHEEL
peepapp_core-0.1.0.dist-info/top_level.txt
peepapp_core-0.1.0.dist-info/RECORD
